checkbox_ng/__init__.py
checkbox_ng/certification.py
checkbox_ng/config.py
checkbox_ng/test_certification.py
checkbox_ng/tests.py
checkbox_ng/urwid_ui.py
checkbox_ng/version.py
checkbox_ng/launcher/__init__.py
checkbox_ng/launcher/check_config.py
checkbox_ng/launcher/checkbox_cli.py
checkbox_ng/launcher/master.py
checkbox_ng/launcher/merge_reports.py
checkbox_ng/launcher/merge_submissions.py
checkbox_ng/launcher/provider_tools.py
checkbox_ng/launcher/run.py
checkbox_ng/launcher/slave.py
checkbox_ng/launcher/stages.py
checkbox_ng/launcher/startprovider.py
checkbox_ng/launcher/subcommands.py
checkbox_ng/launcher/test_inv_run.py
plainbox/__init__.py
plainbox/__main__.py
plainbox/abc.py
plainbox/i18n.py
plainbox/provider_manager.py
plainbox/test_abc.py
plainbox/test_i18n.py
plainbox/test_provider_manager.py
plainbox/tests.py
plainbox/impl/__init__.py
plainbox/impl/_argparse.py
plainbox/impl/_shlex.py
plainbox/impl/_textwrap.py
plainbox/impl/applogic.py
plainbox/impl/box.py
plainbox/impl/buildsystems.py
plainbox/impl/clitools.py
plainbox/impl/color.py
plainbox/impl/ctrl.py
plainbox/impl/decorators.py
plainbox/impl/depmgr.py
plainbox/impl/developer.py
plainbox/impl/execution.py
plainbox/impl/highlevel.py
plainbox/impl/job.py
plainbox/impl/jobcache.py
plainbox/impl/launcher.py
plainbox/impl/logging.py
plainbox/impl/parsers.py
plainbox/impl/pod.py
plainbox/impl/resource.py
plainbox/impl/result.py
plainbox/impl/runner.py
plainbox/impl/symbol.py
plainbox/impl/test_applogic.py
plainbox/impl/test_buildsystems.py
plainbox/impl/test_clitools.py
plainbox/impl/test_color.py
plainbox/impl/test_ctrl.py
plainbox/impl/test_decorators.py
plainbox/impl/test_depmgr.py
plainbox/impl/test_developer.py
plainbox/impl/test_init.py
plainbox/impl/test_launcher.py
plainbox/impl/test_pod.py
plainbox/impl/test_resource.py
plainbox/impl/test_result.py
plainbox/impl/test_runner.py
plainbox/impl/test_symbol.py
plainbox/impl/test_testing_utils.py
plainbox/impl/test_transport.py
checkbox_ng-1.18.1.dist-info/COPYING
checkbox_ng-1.18.1.dist-info/METADATA
checkbox_ng-1.18.1.dist-info/WHEEL
checkbox_ng-1.18.1.dist-info/entry_points.txt
checkbox_ng-1.18.1.dist-info/top_level.txt
checkbox_ng-1.18.1.dist-info/RECORD
