Metadata-Version: 2.1
Name: checkbox-ng
Version: 1.18.1
Summary: Checkbox - Command Line Test Runner
Home-page: https://launchpad.net/checkbox-ng/
Author: Zygmunt Krynicki
Author-email: zygmunt.krynicki@canonical.com
License: GPLv3
Platform: POSIX
Classifier: Development Status :: 5 - Production/Stable
Classifier: Environment :: Console
Classifier: Environment :: Console :: Curses
Classifier: Intended Audience :: Developers
Classifier: Intended Audience :: Information Technology
Classifier: Intended Audience :: Manufacturing
Classifier: License :: OSI Approved :: GNU General Public License v3 (GPLv3)
Classifier: Natural Language :: English
Classifier: Natural Language :: Polish
Classifier: Operating System :: POSIX
Classifier: Operating System :: POSIX :: Linux
Classifier: Programming Language :: Python :: 3.4
Classifier: Topic :: Software Development :: Libraries :: Python Modules
Classifier: Topic :: Software Development :: Quality Assurance
Classifier: Topic :: Software Development :: Testing
Classifier: Topic :: System :: Benchmark
Classifier: Topic :: Utilities
License-File: COPYING
Requires-Dist: Jinja2 (>=2.7)
Requires-Dist: requests (>=1.0)
Requires-Dist: urwid (>=1.1.1)
Requires-Dist: xlsxwriter
